whisperclient/__init__.py
whisperclient/transcriber.py
bezrabotnyiwhisper-0.1.3.dist-info/METADATA
bezrabotnyiwhisper-0.1.3.dist-info/WHEEL
bezrabotnyiwhisper-0.1.3.dist-info/top_level.txt
bezrabotnyiwhisper-0.1.3.dist-info/RECORD
